gv_pubsub/__init__.py
gv_pubsub/pubsub.py
gv_requests/__init__.py
gv_requests/requests.py
gv_service/__init__.py
gv_service/service.py
gv_utils/__init__.py
gv_utils/asyncio.py
gv_utils/csv.py
gv_utils/datetime.py
gv_utils/enums.py
gv_utils/env.py
gv_utils/filesystem.py
gv_utils/geometry.py
gv_utils/logger.py
gv_utils/multicpu.py
gv_utils/parser.py
gv_vendor/__init__.py
gv_vendor/tomtom/ProtobufTrafficFlow_v5_pb2.py
gv_vendor/tomtom/__init__.py
gv_vendor/tomtom/gv_data_pb2.py
gtlv_common-0.0.28.dist-info/LICENSE.txt
gtlv_common-0.0.28.dist-info/METADATA
gtlv_common-0.0.28.dist-info/WHEEL
gtlv_common-0.0.28.dist-info/top_level.txt
gtlv_common-0.0.28.dist-info/RECORD
